odoo9_addon_stock_picking_transfer_lot_autoassign-9.0.1.1.0-py2.7-nspkg.pth
odoo_addons/stock_picking_transfer_lot_autoassign/__openerp__.py
odoo_addons/stock_picking_transfer_lot_autoassign/__init__.py
odoo_addons/stock_picking_transfer_lot_autoassign/README.rst
odoo_addons/stock_picking_transfer_lot_autoassign/models/__init__.py
odoo_addons/stock_picking_transfer_lot_autoassign/models/stock_picking.py
odoo_addons/stock_picking_transfer_lot_autoassign/models/stock_picking_type.py
odoo_addons/stock_picking_transfer_lot_autoassign/i18n/it.po
odoo_addons/stock_picking_transfer_lot_autoassign/i18n/es.po
odoo_addons/stock_picking_transfer_lot_autoassign/i18n/de.po
odoo_addons/stock_picking_transfer_lot_autoassign/i18n/fr.po
odoo_addons/stock_picking_transfer_lot_autoassign/i18n/pt_BR.po
odoo_addons/stock_picking_transfer_lot_autoassign/views/stock_picking_type_view.xml
odoo_addons/stock_picking_transfer_lot_autoassign/wizards/stock_backorder_confirmation.py
odoo_addons/stock_picking_transfer_lot_autoassign/wizards/__init__.py
odoo_addons/stock_picking_transfer_lot_autoassign/wizards/stock_backorder_confirmation.xml
odoo_addons/stock_picking_transfer_lot_autoassign/tests/__init__.py
odoo_addons/stock_picking_transfer_lot_autoassign/tests/test_stock_picking_transfer_lot_autoassign.py
odoo_addons/stock_picking_transfer_lot_autoassign/static/description/icon.png
odoo9_addon_stock_picking_transfer_lot_autoassign-9.0.1.1.0.dist-info/top_level.txt
odoo9_addon_stock_picking_transfer_lot_autoassign-9.0.1.1.0.dist-info/WHEEL
odoo9_addon_stock_picking_transfer_lot_autoassign-9.0.1.1.0.dist-info/RECORD
odoo9_addon_stock_picking_transfer_lot_autoassign-9.0.1.1.0.dist-info/metadata.json
odoo9_addon_stock_picking_transfer_lot_autoassign-9.0.1.1.0.dist-info/DESCRIPTION.rst
odoo9_addon_stock_picking_transfer_lot_autoassign-9.0.1.1.0.dist-info/METADATA
odoo9_addon_stock_picking_transfer_lot_autoassign-9.0.1.1.0.dist-info/namespace_packages.txt
